{"id": 90182, "name": "Ultima", "symbol": "ULTM", "grade": "F", "composite": 32.0, "lc": 5, "ch": 50, "pr": 50, "wallet": "0xab13bA2a5C376E8f9488B80c5B16BA4fdd1850eF", "at": "2026-06-18T17:53:23.000Z", "scored_at": "2026-06-20T16:30:20.220285+00:00", "pre_token": "0xF214793546a495681832930F092ED3aabFE6af2C", "token_address": null, "status": "UNDERGRAD", "sniper_tax": false, "sixtyday_lock": false, "capital_formation": false, "launch_radar": false, "verified": false, "twitter": null, "narrative": "\u2022 Config: Ultima (ULTM) has no sniper tax, no founder 60-day commitment, and no capital formation or launch radar modules.  \u2022 Creator: The wallet has no prior launches, is 0 days old, and has executed only 1 transaction.  \u2022 Presence: The project has documentation but no Twitter handle.", "subscores": {"launch_config": {"antsniper_tax_type": {"label": "Sniper-tax enabled", "value": 0, "score": 0, "max": 30}, "is_project_60days": {"label": "60-day founder commitment", "value": false, "score": 0, "max": 40}, "need_acf": {"label": "Capital Formation module", "value": false, "score": 0, "max": 15}, "launch_radar_enabled": {"label": "Launch Radar module", "value": false, "score": 0, "max": 10}, "airdrop_percent": {"label": "Airdrop allocation", "value": 5, "score": 5, "max": 5}}, "creator_history": {"serial_deployer": {"label": "All-time launches by this wallet", "value": 1, "score": 50, "max": 50}, "wallet_age": {"label": "Creator wallet age", "value": "0d", "score": 0, "max": 30}, "wallet_tx_count": {"label": "Creator wallet tx count", "value": 1, "score": 0, "max": 20}}, "presence": {"twitter": {"label": "Verified Twitter/X linked", "value": "", "score": 0, "max": 40}, "description": {"label": "Substantive description", "value": true, "score": 30, "max": 30}, "project_docs": {"label": "Project documentation present", "value": true, "score": 20, "max": 20}, "is_verified": {"label": "Virtuals verified badge", "value": false, "score": 0, "max": 10}}}}